{
  "en": {
    "lang.toggle.label": "FR",
    "lang.toggle.aria": "Switch to French",
    "theme.toggle.dark": "Night Mode",
    "theme.toggle.light": "Day Mode",
    "theme.toggle.aria.dark": "Switch to light mode",
    "theme.toggle.aria.light": "Switch to dark mode",
    "hero.eyebrow": "Cybersecurity Engineer",
    "hero.cta.primary": "Contact Me",
    "certificates.season6.title": "Hack The Box — Season 6",
    "certificates.season6.summary": "Platinum-tier season finish with a global rank of 632 out of 7,797 contestants.",
    "certificates.season5.title": "Hack The Box — Season 5",
    "certificates.season5.summary": "Maintained Pro Hacker tier while shipping 22 validated compromise reports.",
    "certificates.note": "Click the certificate above to open the official page.",
    "certificates.status": "Certificate 1 of 3",
    "languages.chip.mother": "Mother tongue",
    "languages.chip.bilingual": "Bilingual",
    "languages.chip.advanced": "Advanced",
    "languages.arabic.summary": "Native fluency across personal, academic, and professional contexts.",
    "languages.french.summary": "Full professional proficiency with daily use in engineering programs.",
    "languages.english.summary": "Advanced level validated by TOEIC 850/990 and international teamwork.",
    "contact.form.subject.label": "Subject",
    "contact.form.subject.placeholder": "Brief summary",
    "contact.form.message.label": "Message",
    "contact.form.status.sending": "Sending…",
    "contact.form.status.success": "Message sent successfully — thanks! I will follow up shortly.",
    "contact.form.status.error": "Error while sending the message — please email me at sabir.yassine@proton.me.",
    "contact.form.status.missing": "Form backend not configured — please email me at sabir.yassine@proton.me.",
    "meta.title": "Yassine Sabir | Cybersecurity Engineer",
    "certificates.season6.link": "Open Hack The Box Season 6 certificate in a new tab",
    "certificates.season5.link": "Open Hack The Box Season 5 certificate in a new tab",
    "languages.arabic.label": "Arabic",
    "languages.french.label": "French",
    "languages.english.label": "English",
    "contact.social.linkedin": "LinkedIn",
    "contact.social.github": "GitHub",
    "contact.social.htb": "HackTheBox",
    "certificates.thm.title": "TryHackMe — Offensive Pentesting",
    "certificates.thm.summary": "Completed the Offensive Pentesting learning path covering advanced exploitation and post-exploitation tradecraft.",
    "certificates.thm.link": "Open the TryHackMe certificate in a new tab",
    "hero.stats.rankbadge": "12th in France",
    "hero.stats.availability": "HackTheBox Season 6 national ranking with 100+ rooted machines",
    "htb.cards.challenges.title": "Challenges Solved",
    "htb.cards.challenges.value": "130",
    "htb.cards.challenges.meta": "HackTheBox & CTF labs cleared end-to-end",
    "htb.cards.rank.value": "Pro Hacker",
    "experience.edf.title": "Forensic Analyst Intern – EDF Lab Paris-Saclay",
    "experience.edf.meta": "Palaiseau, France — Mar 2025 ➔ Aug 2025",
    "experience.edf.summary": "Applied research in cybersecurity for industrial programmable logic controllers.",
    "experience.edf.item1": "Performed advanced forensics on PLCs to surface critical evidence and actionable traces.",
    "experience.edf.item2": "Designed and implemented ICS-tailored forensic extraction methods.",
    "experience.edf.item3": "Built Python automation to extract and correlate digital fingerprints, reducing analysis time.",
    "experience.edf.stack": "Technologies: Wireshark, Binwalk, Python",
    "experience.sodimas.title": "Pentester – ESISAR / SODIMAS capstone project",
    "experience.sodimas.meta": "Valence, France — Jan 2024 ➔ Jun 2024",
    "experience.sodimas.summary": "Cybersecurity assessment of a connected elevator platform.",
    "experience.sodimas.item1": "Executed risk analysis and exposed critical vulnerabilities across networks, services, and embedded devices.",
    "experience.sodimas.item2": "Conducted on-site and web intrusion tests proving real attack paths into sensitive services.",
    "experience.sodimas.item3": "Delivered detailed reports with remediation guidance to engineering teams.",
    "experience.sodimas.item4": "Managed the project lifecycle: planning, task tracking, and stakeholder demos.",
    "experience.sodimas.stack": "Technologies: Linux, Nmap, Wireshark, Metasploit, SQLmap, Burp Suite, FFUF, Hydra, DirBuster, GoBuster, OWASP ZAP, Bash, Python",
    "experience.ocp.title": "Web Developer Intern – Groupe OCP",
    "experience.ocp.meta": "Safi, Morocco — Aug 2022",
    "experience.ocp.summary": "Introductory internship focused on building a web portal for internship management.",
    "experience.ocp.item1": "Designed and implemented a staging management portal with reporting features.",
    "experience.ocp.stack": "Technologies: PHP, HTML, CSS, MySQL, TCPDF"
  },
  "fr": {
    "lang.toggle.label": "EN",
    "lang.toggle.aria": "Basculer en anglais",
    "nav.menu": "Menu",
    "nav.about": "Profil",
    "nav.services": "Services",
    "nav.experience": "Expérience",
    "nav.projects": "Projets",
    "nav.achievements": "Réalisations",
    "nav.contact": "Contact",
    "hero.eyebrow": "Ingénieur cybersécurité",
    "hero.subtitle": "Spécialiste offense + défense : outils ICS de réponse à incident, opérations red team et architectures résilientes.",
    "hero.cta.primary": "Me contacter",
    "hero.cta.secondary": "Télécharger le CV",
    "hero.stats.ranking": "Classement mondial HackTheBox Saison 6",
    "hero.stats.availability": "Classement national HackTheBox Saison 6 avec plus de 100 machines compromises",
    "hero.strengths.title": "Forces clés",
    "hero.strengths.badge.offense": "Équipe rouge",
    "hero.strengths.offense": "Émulation d’adversaires sur on-prem, cloud et ICS avec chaînes d’attaque reproductibles.",
    "hero.strengths.badge.ics": "ICS DFIR",
    "hero.strengths.ics": "Forensique et réponse à incident pour automatismes industriels et réseaux OT.",
    "hero.strengths.badge.defense": "Équipe bleue",
    "hero.strengths.defense": "Détection, segmentation zéro-trust et supervision continue des menaces.",
    "about.title": "Transformer la pensée offensive en systèmes résilients",
    "about.intro": "Ingénieur cybersécurité (ESISAR & ENSIAS) : émulation d’adversaires, réponse ICS et architectures durcies pour environnements critiques.",
    "about.terminal.hint": "# Envie d’en savoir plus ? Contactez-moi ;)",
    "about.cards.forensics.title": "Forensique industrielle",
    "about.cards.forensics.body": "Missions ICS : dissection firmware, capture terrain et chasse aux anomalies.",
    "about.cards.pentesting.title": "Tests d’intrusion",
    "about.cards.pentesting.body": "Simulations d’adversaires du threat modeling aux chaînes d’exploitation avec plans de résilience.",
    "about.cards.architecture.title": "Architecture sécurisée",
    "about.cards.architecture.body": "Enclaves zéro-trust connectant identité, segmentation et observabilité sans freiner les équipes.",
    "htb.eyebrow": "Hack The Box",
    "htb.title": "Instantané classement",
    "htb.cards.rank.title": "Rang actuel",
    "htb.cards.rank.value": "Pro Hacker",
    "htb.cards.rank.meta": "Progression vers Elite Hacker",
    "htb.cards.points.title": "Score global",
    "htb.cards.points.value": "102 pts",
    "htb.cards.points.meta": "Classé 854e mondial",
    "htb.cards.systems.title": "Machines rootées",
    "htb.cards.systems.value": "103",
    "htb.cards.systems.meta": "Compromission complète des cibles",
    "htb.cards.users.title": "Accès initiaux",
    "htb.cards.users.value": "111",
    "htb.cards.users.meta": "Trophées niveau utilisateur",
    "pico.eyebrow": "picoCTF",
    "pico.title": "Répartition des challenges",
    "pico.easy.title": "Facile",
    "pico.easy.desc": "61 challenges résolus",
    "pico.medium.title": "Moyen",
    "pico.medium.desc": "94 challenges résolus",
    "pico.hard.title": "Difficile",
    "pico.hard.desc": "3 challenges résolus",
    "services.eyebrow": "Services",
    "services.title": "Mes leviers d’impact",
    "services.assessments.title": "Audits offensifs",
    "services.assessments.item1": "Pentests Web, réseau et embarqué",
    "services.assessments.item2": "Développement d’exploits, élévation de privilèges et mouvement latéral",
    "services.assessments.item3": "Rapports exécutifs et plans d’action",
    "services.ics.title": "Résilience ICS/OT",
    "services.ics.item1": "Préparation forensique pour environnements PLC et OT",
    "services.ics.item2": "Analyse protocolaire et détection d’anomalies",
    "services.ics.item3": "Standards de configuration sécurisée multi-fournisseurs",
    "services.infrastructure.title": "Architecture sécurisée",
    "services.infrastructure.item1": "Segments multi-DMZ avec journalisation centralisée",
    "services.infrastructure.item2": "Durcissement firewall, contrôle VPN et identité",
    "services.infrastructure.item3": "Runbooks opérationnels et documentation",
    "services.enablement.title": "Enablement engineering",
    "services.enablement.item1": "Automatisation Python, Bash, Go",
    "services.enablement.item2": "Coaching champions sécurité",
    "services.enablement.item3": "Table-top et transfert de connaissances",
    "experience.eyebrow": "Expérience",
    "experience.title": "Parcours professionnel",
    "experience.edf.title": "Analyse forensique – Stage de fin d’études EDF Lab Paris-Saclay",
    "experience.edf.meta": "Palaiseau, France — 03/2025 ➔ 08/2025",
    "experience.edf.summary": "Recherche appliquée en cybersécurité des automates programmables industriels.",
    "experience.edf.item1": "Analyses forensiques avancées sur automate industriel pour identifier données critiques et traces exploitables.",
    "experience.edf.item2": "Conception et mise en œuvre de méthodes d’extraction forensique adaptées aux environnements ICS.",
    "experience.edf.item3": "Développement d’outils Python automatisant extraction et corrélation d’empreintes numériques.",
    "experience.edf.stack": "Technologies : Wireshark, Binwalk, Python",
    "experience.sodimas.title": "Pentester – Projet scolaire ESISAR / SODIMAS",
    "experience.sodimas.meta": "Valence, France — 01/2024 ➔ 06/2024",
    "experience.sodimas.summary": "Audit de cybersécurité sur l’architecture numérique d’un ascenseur connecté.",
    "experience.sodimas.item1": "Analyses de risques et identification de vulnérabilités critiques sur réseaux, services et équipements embarqués.",
    "experience.sodimas.item2": "Tests d’intrusion locaux & Web démontrant la compromission de services sensibles.",
    "experience.sodimas.item3": "Rapports détaillés et recommandations présentés aux équipes d’ingénierie.",
    "experience.sodimas.stack": "Technologies : Linux, Nmap, Wireshark, Metasploit, SQLmap, Burp Suite, FFUF, Hydra, DirBuster, GoBuster, OWASP ZAP, Bash, Python",
    "experience.ocp.title": "Développeur Web – Stage d’initiation Groupe OCP",
    "experience.ocp.meta": "Safi, Maroc — 08/2022",
    "experience.ocp.summary": "Stage d’initiation au développement Web pour la gestion des stages au sein de l’entreprise.",
    "experience.ocp.item1": "Conception et réalisation d’un portail de gestion des stages avec génération de rapports.",
    "experience.ocp.item2": "Fonctionnalités de reporting via TCPDF",
    "experience.ocp.stack": "Technologies : PHP, HTML, CSS, MySQL, TCPDF",
    "education.eyebrow": "Formation",
    "education.title": "Parcours académique",
    "education.esisar.title": "Grenoble INP ESISAR",
    "education.esisar.body": "Double diplôme - Informatique, réseaux & cybersécurité - 2023 -- 2025",
    "education.ensias.title": "ENSIAS",
    "education.ensias.body": "Diplôme d’ingénieur - Sécurité des SI - 2021 -- 2023",
    "education.cpge.title": "CPGE Moulay Abdellah",
    "education.cpge.body": "Classes préparatoires - MPSI / MP - 2019 -- 2021",
    "achievements.eyebrow": "Réalisations",
    "achievements.title": "Temps forts",
    "achievements.season.title": "HackTheBox Saison 6",
    "achievements.season.body": "632e sur 7 797 participants : persévérance offensive et travail d’équipe.",
    "achievements.season.cta": "Voir la certification",
    "achievements.france.title": "HackTheBox France 2024",
    "achievements.france.body": "12e national avec plus de 100 machines et 130 challenges.",
    "achievements.france.cta": "Consulter le profil",
    "achievements.research.title": "Publications en cours",
    "achievements.research.body": "Documentation des méthodologies PLC forensics développées au EDF Lab.",
    "languages.eyebrow": "Langues",
    "languages.title": "Atouts de communication",
    "languages.native.quote": "\"Langue maternelle : arabe\"",
    "languages.native.caption": "-- Maîtrise native",
    "languages.other.quote": "\"Français bilingue et anglais avancé (TOEIC 850/990)\"",
    "languages.other.caption": "-- Collaboration internationale efficace",
    "contact.eyebrow": "Contact",
    "contact.title": "Entamons la discussion",
    "contact.details.email": "Email",
    "contact.details.signal": "Signal",
    "contact.details.location": "Localisation",
    "contact.details.locationValue": "Paris, France - Télétravail possible",
    "contact.form.name.label": "Nom",
    "contact.form.name.placeholder": "Votre nom",
    "contact.form.email.label": "Email",
    "contact.form.email.placeholder": "vous@example.com",
    "contact.form.org.label": "Organisation",
    "contact.form.org.placeholder": "Entreprise ou équipe",
    "contact.form.message.label": "Message",
    "contact.form.message.placeholder": "Objectifs, calendrier ou défis actuels",
    "contact.form.submit": "Envoyer la demande",
    "footer.tagline": "© <span id=\"year\"></span> Yassine Sabir. Sécurité sans compromis.",
    "footer.backToTop": "Retour en haut",
    "projects.eyebrow": "Projets",
    "projects.title": "Recherches & builds clés",
    "projects.dmz.title": "Infrastructure multi-DMZ sécurisée",
    "projects.dmz.summary": "Conception et déploiement d’un réseau segmenté avec supervision, annuaire et VPN pour la cyber-range ESISAR.",
    "projects.dmz.focusLabel": "Focus",
    "projects.dmz.focus": "Architecture réseau, durcissement Windows & Linux, SIEM",
    "projects.dmz.stackLabel": "Stack",
    "projects.dmz.stack": "VMware, Windows Server, pfSense, ELK",
    "projects.dmz.cta": "Voir la documentation",
    "projects.terrapin.title": "Détection attaque Terrapin SSH",
    "projects.terrapin.summary": "Capteurs Zeek & Suricata corrélés aux logs AD pour alerter sur Terrapin sur réseaux industriels.",
    "projects.terrapin.outcomeLabel": "Résultat",
    "projects.terrapin.outcome": "Playbooks SOC + règles IDS/IPS prêtes à l’emploi",
    "projects.terrapin.stackLabel": "Stack",
    "projects.terrapin.stack": "Zeek, Suricata, Elastic, Python",
    "projects.terrapin.cta": "Consulter le dépôt",
    "projects.malware.title": "Reverse d’un malware Android bancaire",
    "projects.malware.summary": "Analyse statique/dynamique, extraction de charge utile et IOC publiés pour les blue teams.",
    "projects.malware.focusLabel": "Focus",
    "projects.malware.focus": "Déobfuscation, instrumentation Frida, rédaction IOC",
    "projects.malware.stackLabel": "Stack",
    "projects.malware.stack": "ApkTool, Dex2Jar, JD-GUI, Burp Suite, Frida",
    "projects.malware.cta": "Demander le rapport",
    "skills.eyebrow": "Compétences",
    "skills.title": "Domaines techniques clés",
    "skills.offensive.title": "Sécurité offensive",
    "skills.offensive.item1": "Pentest Web, Linux, Windows",
    "skills.offensive.item2": "Recherche de vulnérabilités & développement d’exploits",
    "skills.offensive.item3": "Méthodologie CTF et reporting",
    "skills.defensive.title": "Architecture défensive",
    "skills.defensive.item1": "Pare-feu, VPN, durcissement LDAP/AD",
    "skills.defensive.item2": "Supervision, IDS et corrélation de logs",
    "skills.defensive.item3": "Analyse de protocoles industriels",
    "skills.programming.title": "Programmation & automatisation",
    "skills.programming.item1": "Python, Bash, Go, Java, C, PHP, JavaScript",
    "skills.programming.item2": "Intégration d’outils sécurité & scripts sur mesure",
    "skills.programming.item3": "Automatisation de pipelines forensics",
    "skills.crypto.title": "Cryptographie & analyse",
    "skills.crypto.item1": "PKI, communications sécurisées, ECIES",
    "skills.crypto.item2": "Reverse engineering et exploitation binaire",
    "skills.crypto.item3": "Dissection de protocoles OT & IT",
    "theme.toggle.dark": "Mode nuit",
    "theme.toggle.light": "Mode jour",
    "theme.toggle.aria.dark": "Basculer en mode clair",
    "theme.toggle.aria.light": "Basculer en mode sombre",
    "certificates.season6.title": "Hack The Box — Saison 6",
    "certificates.season6.summary": "Classement platine, 632e sur 7 797 concurrents au classement mondial.",
    "certificates.season5.title": "Hack The Box — Saison 5",
    "certificates.season5.summary": "Maintien du rang Pro Hacker avec 22 rapports de compromission validés.",
    "certificates.note": "Cliquez sur le certificat pour ouvrir la page officielle.",
    "certificates.status": "Certificat 1 sur 3",
    "languages.chip.mother": "Langue maternelle",
    "languages.chip.bilingual": "Bilingue",
    "languages.chip.advanced": "Avancé",
    "languages.arabic.summary": "Maîtrise native dans les contextes personnels, académiques et professionnels.",
    "languages.french.summary": "Bilingue au quotidien dans les programmes d’ingénierie et livrables techniques.",
    "languages.english.summary": "Niveau avancé attesté par TOEIC 850/990 et collaborations internationales.",
    "contact.form.subject.label": "Objet",
    "contact.form.subject.placeholder": "Résumé rapide",
    "contact.form.status.sending": "Envoi en cours…",
    "contact.form.status.success": "Message envoyé avec succès — merci ! Je vous réponds rapidement.",
    "contact.form.status.error": "Erreur lors de l’envoi du message — contactez-moi sur sabir.yassine@proton.me.",
    "contact.form.status.missing": "Formulaire non configuré — écrivez-moi sur sabir.yassine@proton.me.",
    "meta.title": "Yassine Sabir | Ingénieur cybersécurité",
    "certificates.season6.link": "Ouvrir la certification Hack The Box Saison 6 dans un nouvel onglet",
    "certificates.season5.link": "Ouvrir la certification Hack The Box Saison 5 dans un nouvel onglet",
    "languages.arabic.label": "Arabe",
    "languages.french.label": "Français",
    "languages.english.label": "Anglais",
    "contact.social.linkedin": "LinkedIn",
    "contact.social.github": "GitHub",
    "contact.social.htb": "HackTheBox",
    "certificates.thm.title": "TryHackMe — Offensive Pentesting",
    "certificates.thm.summary": "Parcours Offensive Pentesting complété : exploitation avancée et post-exploitation.",
    "certificates.thm.link": "Ouvrir la certification TryHackMe dans un nouvel onglet",
    "hero.stats.rankbadge": "12e en France",
    "htb.cards.challenges.title": "Challenges résolus",
    "htb.cards.challenges.value": "130",
    "htb.cards.challenges.meta": "Labs HackTheBox et CTF complétés de bout en bout",
    "experience.sodimas.item4": "Gestion de projet : planification, suivi des tâches et présentations intermédiaires."
  }
}
